pyQCDH/__init__.py
pyQCDH/BedBimFam.py
pyQCDH/BimFamReader.py
pyQCDH/ByteDict.py
pyQCDH/collective_intelligence.py
pyQCDH/Gwas.py
pyQCDH/pydata.py
pyQCDH/test.py
pyQCDH-0.0.7.dist-info/DESCRIPTION.rst
pyQCDH-0.0.7.dist-info/METADATA
pyQCDH-0.0.7.dist-info/metadata.json
pyQCDH-0.0.7.dist-info/RECORD
pyQCDH-0.0.7.dist-info/top_level.txt
pyQCDH-0.0.7.dist-info/WHEEL
