Metadata-Version: 2.0
Name: pyQCDH
Version: 0.0.7
Summary: QCDH
Home-page: https://github.com/kindlychung/pyQCDH
Author: Kaiyin Zhong
Author-email: kindlychung@gmail.com
License: UNKNOWN
Keywords: statistics,bioinformatics,GWAS,Genome wide association study
Platform: UNKNOWN
Requires-Dist: pandas
Requires-Dist: statsmodels
Requires-Dist: numpy
